{
  "last_updated": "2025-08-26T21:18:03.685268",
  "news": [
    {
      "title": "「Dr.STONE SCIENCE FUTURE」クライマックスビジュアル、佳境迎える20話の先行カット",
      "link": "https://natalie.mu/comic/news/637573",
      "image_url": "https://ogre.natalie.mu/media/news/comic/2025/0826/ds_ss4_visual.jpg",
      "date": "1900-08-26",
      "timestamp": -2188512000.0
    },
    {
      "title": "ドラマ「絶対BLになる世界VS絶対BLになりたくない男 ファイナル」11月放送開始",
      "link": "https://natalie.mu/comic/news/637494",
      "image_url": "https://ogre.natalie.mu/media/news/comic/2025/0825/zettaiBLfinal_kv.jpg",
      "date": "1900-08-26",
      "timestamp": -2188512000.0
    },
    {
      "title": "「キャッツ♥アイ」OPもAdo、キャッツアイが夜を駆ける予告に神谷も登場",
      "link": "https://natalie.mu/comic/news/637493",
      "image_url": "https://ogre.natalie.mu/media/news/comic/2025/0825/catseye_kv.jpg",
      "date": "1900-08-26",
      "timestamp": -2188512000.0
    },
    {
      "title": "「映画 すみっコぐらし」本予告でとんかつたちの油風呂入浴シーン、主題歌は木村カエラ",
      "link": "https://natalie.mu/comic/news/637460",
      "image_url": "https://ogre.natalie.mu/media/news/comic/2025/0825/sumikkomovie4_poster.jpg",
      "date": "1900-08-26",
      "timestamp": -2188512000.0
    },
    {
      "title": "映画「純愛上等！」美鶴が円に壁ドンする特報、白鳥晴都ら追加キャスト11人発表",
      "link": "https://natalie.mu/comic/news/637457",
      "image_url": "https://ogre.natalie.mu/media/news/comic/2025/0825/junaijoto_movie_teaser.jpg",
      "date": "1900-08-26",
      "timestamp": -2188512000.0
    },
    {
      "title": "「友達の妹が俺にだけウザい」赤見かるび、こはならむの主題歌使用した本PV公開",
      "link": "https://natalie.mu/comic/news/637490",
      "image_url": "https://ogre.natalie.mu/media/news/comic/2025/0825/imouza_KV_logo.jpg",
      "date": "1900-08-25",
      "timestamp": -2188598400.0
    },
    {
      "title": "前屋進「メイドさんは食べるだけ」アニメ化！日本で暮らし始めるメイド役に市ノ瀬加那",
      "link": "https://natalie.mu/comic/news/637415",
      "image_url": "https://ogre.natalie.mu/media/news/comic/2025/0825/meitabe_teaser.jpg",
      "date": "1900-08-25",
      "timestamp": -2188598400.0
    },
    {
      "title": "ショートアニメ「リラックマ」来年4月にテレビ放送開始、ティザービジュアル公開",
      "link": "https://natalie.mu/comic/news/637425",
      "image_url": "https://ogre.natalie.mu/media/news/comic/2025/0825/rilakkuma-teaser.jpg",
      "date": "1900-08-25",
      "timestamp": -2188598400.0
    },
    {
      "title": "「ブサメンガチファイター」もう1人の絶対神・カリナ役は安済知佳",
      "link": "https://natalie.mu/comic/news/637408",
      "image_url": "https://ogre.natalie.mu/media/news/comic/2025/0825/BGF_KV2.jpg",
      "date": "1900-08-25",
      "timestamp": -2188598400.0
    },
    {
      "title": "農業ファンタジーアニメ「異世界のんびり農家」第2期決定！PV＆ビジュアル公開",
      "link": "https://natalie.mu/comic/news/637383",
      "image_url": "https://ogre.natalie.mu/media/news/comic/2025/0824/nonbirinouka2_teaser_01.jpg",
      "date": "1900-08-24",
      "timestamp": -2188684800.0
    },
    {
      "title": "アニメ「Let’s Play」追加キャストに佐倉綾音、日笠陽子ら11人　OP＆EDは久保田利伸",
      "link": "https://natalie.mu/comic/news/637350",
      "image_url": "https://ogre.natalie.mu/media/news/comic/2025/0823/Let_sPlay_mainvisual.jpg",
      "date": "1900-08-24",
      "timestamp": -2188684800.0
    },
    {
      "title": "映画「キミプリ」それぞれを象徴するセリフを添えた、キャラクターポスター全9種",
      "link": "https://natalie.mu/comic/news/637332",
      "image_url": "https://ogre.natalie.mu/media/news/comic/2025/0823/kimipre_poster_01.jpg",
      "date": "1900-08-24",
      "timestamp": -2188684800.0
    },
    {
      "title": "「炎炎ノ消防隊 参ノ章」第2クールのティザービジュアル、シンラたちとアドラ界描く",
      "link": "https://natalie.mu/comic/news/637341",
      "image_url": "https://ogre.natalie.mu/media/news/comic/2025/0823/enen3_2_teaservisual.jpg",
      "date": "1900-08-24",
      "timestamp": -2188684800.0
    },
    {
      "title": "「着せ恋」旭役は河瀬茉希、都役は風間万裕子　「ダブルクラッチ」のポスター公開",
      "link": "https://natalie.mu/comic/news/637323",
      "image_url": "https://ogre.natalie.mu/media/news/comic/2025/0823/BSQ2_akira.jpg",
      "date": "1900-08-24",
      "timestamp": -2188684800.0
    },
    {
      "title": "「スター・ウォーズ：ビジョンズ」Volume3のビジュアル　9つの物語を彩るキャラが集結",
      "link": "https://natalie.mu/comic/news/637282",
      "image_url": "https://ogre.natalie.mu/media/news/comic/2025/0823/SWV_Volume3_kv.jpg",
      "date": "1900-08-23",
      "timestamp": -2188771200.0
    },
    {
      "title": "アニメ「ずたぼろ令嬢」キービジュアル第3弾、スペシャルブックレットのデザイン公開",
      "link": "https://natalie.mu/comic/news/637284",
      "image_url": "https://ogre.natalie.mu/media/news/comic/2025/0823/zutaboro_kv3_logo.jpg",
      "date": "1900-08-23",
      "timestamp": -2188771200.0
    },
    {
      "title": "甲斐谷忍「LIAR GAME」2026年にTVアニメ化！制作はマッドハウス、特報映像公開",
      "link": "https://natalie.mu/comic/news/637281",
      "image_url": "https://ogre.natalie.mu/media/news/comic/2025/0823/LG_teaservisual.jpg",
      "date": "1900-08-23",
      "timestamp": -2188771200.0
    },
    {
      "title": "「よふかしのうた」新章「ハロウィンナイト編」へ、キービジュアル＆PV公開",
      "link": "https://natalie.mu/comic/news/637229",
      "image_url": "https://ogre.natalie.mu/media/news/comic/2025/0822/yofukashi_halloween.jpg",
      "date": "1900-08-23",
      "timestamp": -2188771200.0
    },
    {
      "title": "「シンデレラグレイ」第2クール、海外のライバルたちに甲斐田裕子ら　OPは10-FEET",
      "link": "https://natalie.mu/comic/news/637256",
      "image_url": "https://ogre.natalie.mu/media/news/comic/2025/0822/CinderellaGray2_chara_pv_03.jpg",
      "date": "1900-08-22",
      "timestamp": -2188857600.0
    },
    {
      "title": "「薬屋のひとりごと」夏野菜を穫る猫猫、強い日差しに負けない趙迂の8月ビジュアル",
      "link": "https://natalie.mu/comic/news/637207",
      "image_url": "https://ogre.natalie.mu/media/news/comic/2025/0822/kusuriya_august.jpg",
      "date": "1900-08-22",
      "timestamp": -2188857600.0
    },
    {
      "title": "ヤクザBL「あなたを殺す旅」FODでドラマ化、和田雅成＆高橋大翔がW主演",
      "link": "https://natalie.mu/comic/news/637138",
      "image_url": "https://ogre.natalie.mu/media/news/comic/2025/0822/anatawosagasutabi.jpg",
      "date": "1900-08-22",
      "timestamp": -2188857600.0
    },
    {
      "title": "「終末のワルキューレIII」早見沙織が歌うED曲入りのPV公開、追加キャスト3人も",
      "link": "https://natalie.mu/comic/news/637109",
      "image_url": "https://ogre.natalie.mu/media/news/comic/2025/0821/ragnarok_pv2_01.jpg",
      "date": "1900-08-22",
      "timestamp": -2188857600.0
    },
    {
      "title": "アニメ「ダンダダン」坂田金太役は藤原大智、新たなキービジュアルとPV到着",
      "link": "https://natalie.mu/comic/news/637077",
      "image_url": "https://ogre.natalie.mu/media/news/comic/2025/0821/dandadan2ki_key2.jpg",
      "date": "1900-08-22",
      "timestamp": -2188857600.0
    },
    {
      "title": "アニメ「うるわしの宵の月」宵の友人役に山根綺＆瀬戸桃子",
      "link": "https://natalie.mu/comic/news/637100",
      "image_url": "https://ogre.natalie.mu/media/news/comic/2025/0821/uruwashi_chara01.jpg",
      "date": "1900-08-22",
      "timestamp": -2188857600.0
    },
    {
      "title": "アニメ「補助魔法」メインPV公開、追加キャストに緑川光と阿部敦",
      "link": "https://natalie.mu/comic/news/637040",
      "image_url": "https://ogre.natalie.mu/media/news/comic/2025/0821/hojomaho_kv_tate.jpg",
      "date": "1900-08-21",
      "timestamp": -2188944000.0
    },
    {
      "title": "「LV999の村人」2026年にTVアニメ化、猪股慧士＆東山奈央が出演　ティザーPVも",
      "link": "https://natalie.mu/comic/news/636987",
      "image_url": "https://ogre.natalie.mu/media/news/comic/2025/0821/LV999_Teaser.jpg",
      "date": "1900-08-21",
      "timestamp": -2188944000.0
    },
    {
      "title": "「天使のたまご 4Kリマスター」ポスターを天野喜孝が描き下ろす、制作秘話語る動画も",
      "link": "https://natalie.mu/comic/news/636934",
      "image_url": "https://ogre.natalie.mu/media/news/comic/2025/0820/tentama_poster.jpg",
      "date": "1900-08-21",
      "timestamp": -2188944000.0
    },
    {
      "title": "「桃源暗鬼」第2クール「練馬編」が10月放送開始、追加キャストに土岐隼一ら",
      "link": "https://natalie.mu/comic/news/636923",
      "image_url": "https://ogre.natalie.mu/media/news/comic/2025/0820/tougenanki_kv4.jpg",
      "date": "1900-08-20",
      "timestamp": -2189030400.0
    },
    {
      "title": "「BLUE GIANT」と東方神起がコラボ、石塚真一の描き下ろしイラストがお目見え",
      "link": "https://natalie.mu/comic/news/636935",
      "image_url": "https://ogre.natalie.mu/media/news/comic/2025/0820/tohoshinki_bluegiant_collabo.jpg",
      "date": "1900-08-20",
      "timestamp": -2189030400.0
    }
  ]
}